kitsu/__init__.py
kitsu/client.py
kitsu/errors.py
kitsu/models.py
kitsu/py.typed
LICENSE
kitsu_py-1.1.2.dist-info/LICENSE
kitsu_py-1.1.2.dist-info/METADATA
kitsu_py-1.1.2.dist-info/WHEEL
kitsu_py-1.1.2.dist-info/RECORD
