Metadata-Version: 2.1
Name: kitsu-py
Version: 1.1.2
Summary: A Simple & Lightweight Asynchronous Python Wrapper for Kitsu's Manga & Anime API.
Home-page: https://github.com/MrArkon/kitsu.py/
License: MIT
Keywords: kitsu,async kitsu,kitsu.py,kitsu api wrapper
Author: MrArkon
Author-email: mrarkon@outlook.com
Maintainer: MrArkon
Maintainer-email: mrarkon@outlook.com
Requires-Python: >=3.8,<4.0
Classifier: Intended Audience :: Developers
Classifier: License :: OSI Approved :: MIT License
Classifier: Natural Language :: English
Classifier: Operating System :: OS Independent
Classifier: Programming Language :: Python :: 3
Classifier: Programming Language :: Python :: 3.8
Classifier: Programming Language :: Python :: 3.9
Classifier: Programming Language :: Python :: 3.10
Classifier: Programming Language :: Python :: 3.11
Classifier: Topic :: Games/Entertainment
Classifier: Topic :: Internet
Classifier: Topic :: Software Development :: Libraries
Classifier: Topic :: Software Development :: Libraries :: Python Modules
Classifier: Topic :: Utilities
Classifier: Typing :: Typed
Requires-Dist: aiohttp (>=3.7.4,<4.0.0)
Requires-Dist: python-dateutil (>=2.8.2,<3.0.0)
Project-URL: Bug Tracker, https://github.com/MrArkon/kitsu.py/issues
Project-URL: Changelog, https://github.com/MrArkon/kitsu.py/blob/master/CHANGELOG.md
Project-URL: Documentation, https://kitsu-py.readthedocs.io/en/stable/
Project-URL: Repository, https://github.com/MrArkon/kitsu.py/
